chatgpt_cli/__init__.py
chatgpt_cli/main.py
simple_chatgpt_cli-0.1.11.dist-info/METADATA
simple_chatgpt_cli-0.1.11.dist-info/WHEEL
simple_chatgpt_cli-0.1.11.dist-info/entry_points.txt
simple_chatgpt_cli-0.1.11.dist-info/RECORD
