Metadata-Version: 2.1
Name: simple-chatgpt-cli
Version: 0.1.11
Summary: 
Author: tailaiw
Author-email: 29800495+tailaiw@users.noreply.github.com
Requires-Python: >=3.10,<3.12
Classifier: Programming Language :: Python :: 3
Classifier: Programming Language :: Python :: 3.10
Classifier: Programming Language :: Python :: 3.11
Requires-Dist: openai (>=0.27.6,<0.28.0)
Requires-Dist: rich (>=13.3.5,<14.0.0)
